fin_trend_analyzer/__init__.py
fin_trend_analyzer/main.py
fin_trend_analyzer/prompts.py
fin_trend_analyzer-2025.12.21233059.dist-info/METADATA
fin_trend_analyzer-2025.12.21233059.dist-info/WHEEL
fin_trend_analyzer-2025.12.21233059.dist-info/top_level.txt
fin_trend_analyzer-2025.12.21233059.dist-info/RECORD
