Metadata-Version: 2.4
Name: fin-trend-analyzer
Version: 2025.12.21233059
Summary: fin-trend-analyzer analyzes financial news and sentiment to identify trends and risks in AI and tech stocks, providing structured insights for quick market assessment.
Author-email: fin-trend-analyzer <hi@eugene.plus>
License: MIT
Project-URL: Homepage, https://github.com/chigwell/fin-trend-analyzer
Requires-Python: >=3.9
Requires-Dist: langchain-llm7>=0.0.0
Requires-Dist: llmatch-messages>=0.0.0
Requires-Dist: langchain-core>=0.3.0
